conjurl/__init__.py
conjurl/py.typed
conjurl-0.1.0.dev0.dist-info/WHEEL
conjurl-0.1.0.dev0.dist-info/METADATA
conjurl-0.1.0.dev0.dist-info/RECORD
