Metadata-Version: 2.3
Name: conjurl
Version: 0.1.0.dev0
Summary: Conjurl is a Python crime which is meant to allow importing from various URLs (and URIs).
Author: Joshua Cannon
Author-email: Joshua Cannon <thejcannon@gmail.com>
License: Copyright 2025 @thejcannon
Requires-Python: >=3.11
